fds/__init__.py
fds/sdk/__init__.py
fds/sdk/FactSetConcordance/__init__.py
fds/sdk/FactSetConcordance/api_client.py
fds/sdk/FactSetConcordance/configuration.py
fds/sdk/FactSetConcordance/exceptions.py
fds/sdk/FactSetConcordance/model_utils.py
fds/sdk/FactSetConcordance/rest.py
fds/sdk/FactSetConcordance/api/__init__.py
fds/sdk/FactSetConcordance/api/entity_match___bulk_api.py
fds/sdk/FactSetConcordance/api/entity_match_api.py
fds/sdk/FactSetConcordance/api/mappings_api.py
fds/sdk/FactSetConcordance/api/people_mapping_api.py
fds/sdk/FactSetConcordance/api/people_match___bulk_api.py
fds/sdk/FactSetConcordance/api/people_match_api.py
fds/sdk/FactSetConcordance/api/snowflake_api.py
fds/sdk/FactSetConcordance/api/universes_api.py
fds/sdk/FactSetConcordance/apis/__init__.py
fds/sdk/FactSetConcordance/model/__init__.py
fds/sdk/FactSetConcordance/model/create_universe_request.py
fds/sdk/FactSetConcordance/model/entity_decisions_response.py
fds/sdk/FactSetConcordance/model/entity_mapping.py
fds/sdk/FactSetConcordance/model/entity_mapping_delete_request.py
fds/sdk/FactSetConcordance/model/entity_mapping_delete_response.py
fds/sdk/FactSetConcordance/model/entity_mapping_request.py
fds/sdk/FactSetConcordance/model/entity_mapping_response.py
fds/sdk/FactSetConcordance/model/entity_match.py
fds/sdk/FactSetConcordance/model/entity_match_request.py
fds/sdk/FactSetConcordance/model/entity_match_request_input.py
fds/sdk/FactSetConcordance/model/entity_matches_response.py
fds/sdk/FactSetConcordance/model/entity_response.py
fds/sdk/FactSetConcordance/model/entity_task_response.py
fds/sdk/FactSetConcordance/model/entity_task_status.py
fds/sdk/FactSetConcordance/model/entity_task_status_response.py
fds/sdk/FactSetConcordance/model/entity_universe_request.py
fds/sdk/FactSetConcordance/model/entity_universe_response.py
fds/sdk/FactSetConcordance/model/entity_universe_statistics_response.py
fds/sdk/FactSetConcordance/model/error_response.py
fds_sdk_factsetconcordance-2.0.1.dist-info/licenses/LICENSE
fds_sdk_factsetconcordance-2.0.1.dist-info/METADATA
fds_sdk_factsetconcordance-2.0.1.dist-info/WHEEL
fds_sdk_factsetconcordance-2.0.1.dist-info/top_level.txt
fds_sdk_factsetconcordance-2.0.1.dist-info/RECORD
